pynetwork/Controller.py
pynetwork/Gateway.py
pynetwork/Handshakes.py
pynetwork/SubroutineStreamer.py
pynetwork/Subroutines.py
pynetwork/__init__.py
pynetwork/backend.py
pynetwork/backend2.py
pynetwork-2.4.dist-info/LICENSE
pynetwork-2.4.dist-info/METADATA
pynetwork-2.4.dist-info/WHEEL
pynetwork-2.4.dist-info/top_level.txt
pynetwork-2.4.dist-info/RECORD
