Metadata-Version: 2.1
Name: pynetwork
Version: 2.4
Summary: package to manage connection swarms for your network workloads
Home-page: https://github.com/nirajkale/pynetwork
Author: Niraj S. Kale
Author-email: nirajkale157@outlook.com
License: UNKNOWN
Platform: UNKNOWN
Classifier: Programming Language :: Python :: 3
Classifier: License :: OSI Approved :: Apache Software License
Classifier: Operating System :: OS Independent
